{
  "default_video": "default_loop.mp4",
  "videos": [
    {
      "id": "01",
      "name": "Soda Pop",
      "file": "videos/soda_pop.mp4",
      "poster": "/static/posters/soda_pop.jpg",
      "dmx_template": "soda_pop_dmx.json"
    },
    {
      "id": "02",
      "name": "Idol",
      "file": "videos/idol.mp4",
      "poster": "/static/posters/idol.jpg",
      "dmx_template": "idol_dmx.json"
    },
    {
      "id": "02",
      "name": "This Is What It Sounds Like",
      "file": "videos/sounds_like.mp4",
      "poster": "/static/posters/sounds_like.jpg",
      "dmx_template": "sounds_like_dmx.json"
    }
  ]
}
